compose_dump/__init__.py
compose_dump/backup.py
compose_dump/main.py
compose_dump/storage.py
compose_dump/utils.py
compose_dump-0.1b4.dist-info/DESCRIPTION.rst
compose_dump-0.1b4.dist-info/METADATA
compose_dump-0.1b4.dist-info/RECORD
compose_dump-0.1b4.dist-info/WHEEL
compose_dump-0.1b4.dist-info/entry_points.txt
compose_dump-0.1b4.dist-info/metadata.json
compose_dump-0.1b4.dist-info/top_level.txt
