Metadata-Version: 2.0
Name: compose-dump
Version: 0.1b4
Summary: Backup tool for Docker Compose projects
Home-page: http://compose-dump.rtfd.io/
Author: Frank Sachsenheim
Author-email: funkyfuture@riseup.net
License: ISC
Keywords: docker-compose backup archiving
Platform: any
Classifier: Development Status :: 4 - Beta
Classifier: Environment :: Console
Classifier: Intended Audience :: System Administrators
Classifier: License :: OSI Approved :: ISC License (ISCL)
Classifier: Operating System :: POSIX
Classifier: Programming Language :: Python
Classifier: Programming Language :: Python :: 3
Classifier: Programming Language :: Python :: 3.4
Classifier: Programming Language :: Python :: 3.5
Classifier: Programming Language :: Python :: 3.6
Classifier: Programming Language :: Python :: Implementation :: CPython
Classifier: Topic :: System :: Archiving :: Backup
Requires-Dist: docker-compose (<1.20,>=1.7)
